{
  "schema_version": 1,
  "pricing_model_version": "black_scholes_single_strike_v1",
  "summary": {
    "matched_count": 0,
    "rejected_count": 1,
    "rejection_counts": [
      {
        "reason": "EdgeBelowThreshold",
        "count": 1
      }
    ],
    "net_edge": {
      "sample_count": 0,
      "average": null,
      "min": null,
      "max": null
    }
  },
  "entries": [
    {
      "type": "rejected",
      "reason": "EdgeBelowThreshold",
      "deribit_instrument_id": "ETH-20260601-3000-C",
      "polymarket_market_slug": "eth-above-3000-wide-spread"
    }
  ]
}
